MANIFEST.in
README.md
setup.py
elyzer/__init__.py
elyzer/__main__.py
elyzer/elyzer.py
elyzer/envDefault.py
elyzer.egg-info/PKG-INFO
elyzer.egg-info/SOURCES.txt
elyzer.egg-info/dependency_links.txt
elyzer.egg-info/entry_points.txt
elyzer.egg-info/requires.txt
elyzer.egg-info/top_level.txt