Metadata-Version: 1.1
Name: elyzer
Version: 1.2.1
Summary: Step-by-Step Debug Elasticsearch Analyzers
Home-page: https://github.com/o19s/elyzer
Author: Doug Turnbull
Author-email: dturnbull@o19s.com
License: Apache
Keywords: elasticsearch,database
Platform: UNKNOWN
Classifier: Environment :: Console
Classifier: Intended Audience :: Developers
Classifier: Intended Audience :: System Administrators
Classifier: License :: OSI Approved :: Apache Software License
Classifier: Natural Language :: English
Classifier: Programming Language :: Python :: 3
Classifier: Topic :: Utilities
